django_accept_header/__init__.py
django_accept_header/header.py
django_accept_header/middleware.py
django_accept_header-0.3.2.dist-info/DESCRIPTION.rst
django_accept_header-0.3.2.dist-info/METADATA
django_accept_header-0.3.2.dist-info/RECORD
django_accept_header-0.3.2.dist-info/WHEEL
django_accept_header-0.3.2.dist-info/metadata.json
django_accept_header-0.3.2.dist-info/pbr.json
django_accept_header-0.3.2.dist-info/top_level.txt
