Metadata-Version: 2.0
Name: django-accept-header
Version: 0.3.2
Summary: A Django middleware that inspects the HTTP Accept headers sent by browsers.
Home-page: https://github.com/fladi/django-accept-header
Author: Michael Fladischer
Author-email: michael@fladi.at
License: BSD
Keywords: middleware,header,accept,mimetype
Platform: UNKNOWN
Classifier: Development Status :: 4 - Beta
Classifier: Framework :: Django
Classifier: Framework :: Django :: 1.8
Classifier: Intended Audience :: Developers
Classifier: License :: OSI Approved :: ISC License (ISCL)
Classifier: Programming Language :: Python
Classifier: Programming Language :: Python :: 2.7
Classifier: Programming Language :: Python :: 3
Classifier: Programming Language :: Python :: 3.4
Classifier: Programming Language :: Python :: 3.5
Classifier: Programming Language :: Python :: Implementation :: CPython
Classifier: Programming Language :: Python :: Implementation :: PyPy
Classifier: Topic :: Utilities
Requires-Dist: Django
Provides-Extra: rst
Requires-Dist: docutils (>=0.11); extra == 'rst'
Provides-Extra: testing
Requires-Dist: pytest; extra == 'testing'
